flask_tabler_icons/__init__.py
flask_tabler_icons/static/tabler_icons/tabler-sprite-filled.svg
flask_tabler_icons/static/tabler_icons/tabler-sprite-nostroke.svg
flask_tabler_icons/templates/tabler_icons/helper.html
flask_tabler_icons-3.35.0.20250916.dist-info/licenses/LICENSE.txt
flask_tabler_icons-3.35.0.20250916.dist-info/METADATA
flask_tabler_icons-3.35.0.20250916.dist-info/WHEEL
flask_tabler_icons-3.35.0.20250916.dist-info/top_level.txt
flask_tabler_icons-3.35.0.20250916.dist-info/RECORD
