Metadata-Version: 2.4
Name: flask_tabler_icons
Version: 3.35.0.20250916
Summary: a collection of jinja macros for tabler icons
Author-email: Lix Xu <xuzenglin@gmail.com>
Project-URL: Homepage, https://github.com/lixxu/flask-tabler-icons
Project-URL: Bug Tracker, https://github.com/lixxu/flask-tabler-icons/issues
Keywords: flask_tabler,flask_tabler_icons
Classifier: Intended Audience :: Developers
Classifier: Operating System :: OS Independent
Classifier: Programming Language :: Python :: 3
Classifier: Development Status :: 5 - Production/Stable
Requires-Python: >=3.8
License-File: LICENSE.txt
Requires-Dist: flask
Requires-Dist: flask_topassets
Dynamic: license-file
